{
  "_meta": {
    "reciter": "salah_alhashim_qalon",
    "name_en": "Salah Alhashim",
    "name_ar": "صلاح الهاشم",
    "riwayah": "qalon_an_nafi",
    "style": "murattal",
    "audio_category": "by_surah",
    "source": "https://mp3quran.net/",
    "country": "unknown",
    "_timing": {
      "source": "mp3quran_api",
      "type": "verse",
      "data": {
        "1": [
          [
            5880,
            10680
          ],
          [
            10680,
            16040
          ],
          [
            16040,
            19700
          ],
          [
            19700,
            23540
          ],
          [
            23540,
            28900
          ],
          [
            28900,
            33560
          ],
          [
            33560,
            45980
          ]
        ],
        "12": [
          [
            5340,
            14060
          ],
          [
            14060,
            25100
          ],
          [
            25100,
            49760
          ],
          [
            49760,
            69880
          ],
          [
            69880,
            86740
          ],
          [
            86740,
            120820
          ],
          [
            120820,
            131840
          ],
          [
            131840,
            147580
          ],
          [
            147580,
            164880
          ],
          [
            164880,
            185280
          ],
          [
            185280,
            197760
          ],
          [
            197760,
            207000
          ],
          [
            207000,
            226720
          ],
          [
            226720,
            236680
          ],
          [
            236680,
            258220
          ],
          [
            258220,
            268180
          ],
          [
            268180,
            294100
          ],
          [
            294100,
            316420
          ],
          [
            316420,
            338280
          ],
          [
            338280,
            349200
          ],
          [
            349200,
            390860
          ],
          [
            390860,
            404060
          ],
          [
            404060,
            429940
          ],
          [
            429940,
            452200
          ],
          [
            452200,
            477060
          ],
          [
            477060,
            500920
          ],
          [
            500920,
            510860
          ],
          [
            510860,
            527280
          ],
          [
            527280,
            539400
          ],
          [
            539400,
            558500
          ],
          [
            558500,
            604100
          ],
          [
            604100,
            627160
          ],
          [
            627160,
            647180
          ],
          [
            647180,
            658660
          ],
          [
            658660,
            669920
          ],
          [
            669920,
            703360
          ],
          [
            703360,
            732000
          ],
          [
            732000,
            761740
          ],
          [
            761740,
            772460
          ],
          [
            772460,
            817540
          ],
          [
            817540,
            838100
          ],
          [
            838100,
            860820
          ],
          [
            860820,
            895740
          ],
          [
            895740,
            907620
          ],
          [
            907620,
            920040
          ],
          [
            920040,
            952920
          ],
          [
            952920,
            970920
          ],
          [
            970920,
            989740
          ],
          [
            989740,
            1000780
          ],
          [
            1000780,
            1024400
          ],
          [
            1024400,
            1053040
          ],
          [
            1053040,
            1066140
          ],
          [
            1066140,
            1085760
          ],
          [
            1085760,
            1102120
          ],
          [
            1102120,
            1111580
          ],
          [
            1111580,
            1131200
          ],
          [
            1131200,
            1139840
          ],
          [
            1139840,
            1152900
          ],
          [
            1152900,
            1171900
          ],
          [
            1171900,
            1180680
          ],
          [
            1180680,
            1188240
          ],
          [
            1188240,
            1209520
          ],
          [
            1209520,
            1237600
          ],
          [
            1237600,
            1259020
          ],
          [
            1259020,
            1288840
          ],
          [
            1288840,
            1317960
          ],
          [
            1317960,
            1349280
          ],
          [
            1349280,
            1384440
          ],
          [
            1384440,
            1402300
          ],
          [
            1402300,
            1422060
          ],
          [
            1422060,
            1428860
          ],
          [
            1428860,
            1440580
          ],
          [
            1440580,
            1451220
          ],
          [
            1451220,
            1460280
          ],
          [
            1460280,
            1473300
          ],
          [
            1473300,
            1514440
          ],
          [
            1514440,
            1539700
          ],
          [
            1539700,
            1559360
          ],
          [
            1559360,
            1573880
          ],
          [
            1573880,
            1610120
          ],
          [
            1610120,
            1637740
          ],
          [
            1637740,
            1652740
          ],
          [
            1652740,
            1674500
          ],
          [
            1674500,
            1694000
          ],
          [
            1694000,
            1705360
          ],
          [
            1705360,
            1720660
          ],
          [
            1720660,
            1742960
          ],
          [
            1742960,
            1779420
          ],
          [
            1779420,
            1790980
          ],
          [
            1790980,
            1816540
          ],
          [
            1816540,
            1827260
          ],
          [
            1827260,
            1839160
          ],
          [
            1839160,
            1852200
          ],
          [
            1852200,
            1867320
          ],
          [
            1867320,
            1874120
          ],
          [
            1874120,
            1895400
          ],
          [
            1895400,
            1907240
          ],
          [
            1907240,
            1917200
          ],
          [
            1917200,
            1936080
          ],
          [
            1936080,
            1994120
          ],
          [
            1994120,
            2019860
          ],
          [
            2019860,
            2036640
          ],
          [
            2036640,
            2044820
          ],
          [
            2044820,
            2053659
          ],
          [
            2053659,
            2065500
          ],
          [
            2065500,
            2074000
          ],
          [
            2074000,
            2092199
          ],
          [
            2092199,
            2111880
          ],
          [
            2111880,
            2142360
          ],
          [
            2142360,
            2169700
          ],
          [
            2169700,
            2199340
          ]
        ],
        "40": [
          [
            6420,
            9420
          ],
          [
            9420,
            17600
          ],
          [
            17600,
            32400
          ],
          [
            32400,
            45520
          ],
          [
            45520,
            73480
          ],
          [
            73480,
            85800
          ],
          [
            85800,
            121680
          ],
          [
            121680,
            144400
          ],
          [
            144400,
            160460
          ],
          [
            160460,
            180220
          ],
          [
            180220,
            200220
          ],
          [
            200220,
            219000
          ],
          [
            219000,
            235760
          ],
          [
            235760,
            243920
          ],
          [
            243920,
            263400
          ],
          [
            263400,
            283340
          ],
          [
            283340,
            298160
          ],
          [
            298160,
            316600
          ],
          [
            316600,
            325320
          ],
          [
            325320,
            342500
          ],
          [
            342500,
            375520
          ],
          [
            375520,
            395140
          ],
          [
            395140,
            404320
          ],
          [
            404320,
            413700
          ],
          [
            413700,
            447880
          ],
          [
            447880,
            467020
          ],
          [
            467020,
            486240
          ],
          [
            486240,
            537800
          ],
          [
            537800,
            567900
          ],
          [
            567900,
            581860
          ],
          [
            581860,
            596700
          ],
          [
            596700,
            605140
          ],
          [
            605140,
            619380
          ],
          [
            619380,
            656360
          ],
          [
            656360,
            683640
          ],
          [
            683640,
            694200
          ],
          [
            694200,
            722360
          ],
          [
            722360,
            732880
          ],
          [
            732880,
            746060
          ],
          [
            746060,
            776980
          ],
          [
            776980,
            790120
          ],
          [
            790120,
            805160
          ],
          [
            805160,
            833860
          ],
          [
            833860,
            852960
          ],
          [
            852960,
            864660
          ],
          [
            864660,
            881880
          ],
          [
            881880,
            914240
          ],
          [
            914240,
            929160
          ],
          [
            929160,
            943700
          ],
          [
            943700,
            964680
          ],
          [
            964680,
            977720
          ],
          [
            977720,
            990520
          ],
          [
            990520,
            1002820
          ],
          [
            1002820,
            1007980
          ],
          [
            1007980,
            1025599
          ],
          [
            1025599,
            1057680
          ],
          [
            1057680,
            1070960
          ],
          [
            1070960,
            1087820
          ],
          [
            1087820,
            1100740
          ],
          [
            1100740,
            1119340
          ],
          [
            1119340,
            1141400
          ],
          [
            1141400,
            1156520
          ],
          [
            1156520,
            1165400
          ],
          [
            1165400,
            1196240
          ],
          [
            1196240,
            1212740
          ],
          [
            1212740,
            1235340
          ],
          [
            1235340,
            1277920
          ],
          [
            1277920,
            1294240
          ],
          [
            1294240,
            1305840
          ],
          [
            1305840,
            1318920
          ],
          [
            1318920,
            1328420
          ],
          [
            1328420,
            1335960
          ],
          [
            1335960,
            1344460
          ],
          [
            1344460,
            1362700
          ],
          [
            1362700,
            1375980
          ],
          [
            1375980,
            1388540
          ],
          [
            1388540,
            1405660
          ],
          [
            1405660,
            1440480
          ],
          [
            1440480,
            1450980
          ],
          [
            1450980,
            1465500
          ],
          [
            1465500,
            1474620
          ],
          [
            1474620,
            1507140
          ],
          [
            1507140,
            1531500
          ],
          [
            1531500,
            1546780
          ],
          [
            1546780,
            1566980
          ]
        ],
        "50": [
          [
            5340,
            13400
          ],
          [
            13400,
            32439
          ],
          [
            32439,
            41240
          ],
          [
            41240,
            51420
          ],
          [
            51420,
            63420
          ],
          [
            63420,
            81660
          ],
          [
            81660,
            98300
          ],
          [
            98300,
            105380
          ],
          [
            105380,
            123720
          ],
          [
            123720,
            131260
          ],
          [
            131260,
            143400
          ],
          [
            143400,
            151340
          ],
          [
            151340,
            157100
          ],
          [
            157100,
            166840
          ],
          [
            166840,
            177360
          ],
          [
            177360,
            190460
          ],
          [
            190460,
            198800
          ],
          [
            198800,
            206540
          ],
          [
            206540,
            218520
          ],
          [
            218520,
            226220
          ],
          [
            226220,
            236660
          ],
          [
            236660,
            256800
          ],
          [
            256800,
            263460
          ],
          [
            263460,
            270600
          ],
          [
            270600,
            277600
          ],
          [
            277600,
            287900
          ],
          [
            287900,
            300820
          ],
          [
            300820,
            309820
          ],
          [
            309820,
            319460
          ],
          [
            319460,
            328660
          ],
          [
            328660,
            335620
          ],
          [
            335620,
            342340
          ],
          [
            342340,
            351720
          ],
          [
            351720,
            359600
          ],
          [
            359600,
            368320
          ],
          [
            368320,
            383960
          ],
          [
            383960,
            394700
          ],
          [
            394700,
            407020
          ],
          [
            407020,
            417480
          ],
          [
            417480,
            423680
          ],
          [
            423680,
            431620
          ],
          [
            431620,
            439460
          ],
          [
            439460,
            446540
          ],
          [
            446540,
            456000
          ],
          [
            456000,
            475000
          ]
        ],
        "53": [
          [
            5460,
            8440
          ],
          [
            8440,
            12480
          ],
          [
            12480,
            16120
          ],
          [
            16120,
            20260
          ],
          [
            20260,
            23740
          ],
          [
            23740,
            27420
          ],
          [
            27420,
            30520
          ],
          [
            30520,
            34160
          ],
          [
            34160,
            38280
          ],
          [
            38280,
            45540
          ],
          [
            45540,
            49060
          ],
          [
            49060,
            53280
          ],
          [
            53280,
            57040
          ],
          [
            57040,
            61320
          ],
          [
            61320,
            65780
          ],
          [
            65780,
            69400
          ],
          [
            69400,
            73000
          ],
          [
            73000,
            77800
          ],
          [
            77800,
            81480
          ],
          [
            81480,
            85020
          ],
          [
            85020,
            89380
          ],
          [
            89380,
            94180
          ],
          [
            94180,
            130979
          ],
          [
            130979,
            135800
          ],
          [
            135800,
            139760
          ],
          [
            139760,
            161340
          ],
          [
            161340,
            173500
          ],
          [
            173500,
            187540
          ],
          [
            187540,
            197020
          ],
          [
            197020,
            211040
          ],
          [
            211040,
            226000
          ],
          [
            226000,
            260019
          ],
          [
            260019,
            263500
          ],
          [
            263500,
            267300
          ],
          [
            267300,
            272160
          ],
          [
            272160,
            276740
          ],
          [
            276740,
            280300
          ],
          [
            280300,
            285120
          ],
          [
            285120,
            290700
          ],
          [
            290700,
            294800
          ],
          [
            294800,
            300940
          ],
          [
            300940,
            305840
          ],
          [
            305840,
            309960
          ],
          [
            309960,
            314400
          ],
          [
            314400,
            320980
          ],
          [
            320980,
            324460
          ],
          [
            324460,
            329140
          ],
          [
            329140,
            333560
          ],
          [
            333560,
            337360
          ],
          [
            337360,
            342580
          ],
          [
            342580,
            346680
          ],
          [
            346680,
            354880
          ],
          [
            354880,
            357860
          ],
          [
            357860,
            360980
          ],
          [
            360980,
            366920
          ],
          [
            366920,
            372560
          ],
          [
            372560,
            374960
          ],
          [
            374960,
            380080
          ],
          [
            380080,
            384980
          ],
          [
            384980,
            389460
          ],
          [
            389460,
            393900
          ],
          [
            393900,
            397420
          ]
        ],
        "75": [
          [
            4840,
            9420
          ],
          [
            9420,
            15080
          ],
          [
            15080,
            21100
          ],
          [
            21100,
            27500
          ],
          [
            27500,
            32580
          ],
          [
            32580,
            36080
          ],
          [
            36080,
            38720
          ],
          [
            38720,
            40560
          ],
          [
            40560,
            43240
          ],
          [
            43240,
            48400
          ],
          [
            48400,
            50540
          ],
          [
            50540,
            54420
          ],
          [
            54420,
            61680
          ],
          [
            61680,
            66640
          ],
          [
            66640,
            69960
          ],
          [
            69960,
            74520
          ],
          [
            74520,
            79020
          ],
          [
            79020,
            83340
          ],
          [
            83340,
            87800
          ],
          [
            87800,
            91340
          ],
          [
            91340,
            93980
          ],
          [
            93980,
            98560
          ],
          [
            98560,
            101360
          ],
          [
            101360,
            106040
          ],
          [
            106040,
            110660
          ],
          [
            110660,
            116340
          ],
          [
            116340,
            120860
          ],
          [
            120860,
            125440
          ],
          [
            125440,
            129699
          ],
          [
            129699,
            134460
          ],
          [
            134460,
            137520
          ],
          [
            137520,
            141440
          ],
          [
            141440,
            147040
          ],
          [
            147040,
            149580
          ],
          [
            149580,
            153100
          ],
          [
            153100,
            158540
          ],
          [
            158540,
            163920
          ],
          [
            163920,
            169420
          ],
          [
            169420,
            174960
          ],
          [
            174960,
            182720
          ]
        ],
        "76": [
          [
            4760,
            14480
          ],
          [
            14480,
            27060
          ],
          [
            27060,
            35680
          ],
          [
            35680,
            44820
          ],
          [
            44820,
            53280
          ],
          [
            53280,
            60780
          ],
          [
            60780,
            69160
          ],
          [
            69160,
            77760
          ],
          [
            77760,
            88420
          ],
          [
            88420,
            95420
          ],
          [
            95420,
            104000
          ],
          [
            104000,
            110160
          ],
          [
            110160,
            120820
          ],
          [
            120820,
            128060
          ],
          [
            128060,
            138340
          ],
          [
            138340,
            144820
          ],
          [
            144820,
            152060
          ],
          [
            152060,
            157200
          ],
          [
            157200,
            167660
          ],
          [
            167660,
            175640
          ],
          [
            175640,
            191440
          ],
          [
            191440,
            201080
          ],
          [
            201080,
            207720
          ],
          [
            207720,
            214500
          ],
          [
            214500,
            219240
          ],
          [
            219240,
            226040
          ],
          [
            226040,
            239540
          ],
          [
            239540,
            251760
          ],
          [
            251760,
            261899
          ],
          [
            261899,
            277060
          ],
          [
            277060,
            287920
          ]
        ]
      }
    },
    "fetched": "2026-03-28"
  },
  "1": "https://server12.mp3quran.net/salah_hashim_m/Rewayat-Qalon-A-n-Nafi/001.mp3",
  "12": "https://server12.mp3quran.net/salah_hashim_m/Rewayat-Qalon-A-n-Nafi/012.mp3",
  "40": "https://server12.mp3quran.net/salah_hashim_m/Rewayat-Qalon-A-n-Nafi/040.mp3",
  "50": "https://server12.mp3quran.net/salah_hashim_m/Rewayat-Qalon-A-n-Nafi/050.mp3",
  "53": "https://server12.mp3quran.net/salah_hashim_m/Rewayat-Qalon-A-n-Nafi/053.mp3",
  "75": "https://server12.mp3quran.net/salah_hashim_m/Rewayat-Qalon-A-n-Nafi/075.mp3",
  "76": "https://server12.mp3quran.net/salah_hashim_m/Rewayat-Qalon-A-n-Nafi/076.mp3"
}
